kotti_group_manager/__init__.py
kotti_group_manager/__init__.pyc
kotti_group_manager/controlpanel.py
kotti_group_manager/controlpanel.pyc
kotti_group_manager/fanstatic.py
kotti_group_manager/fanstatic.pyc
kotti_group_manager/populator.py
kotti_group_manager/populator.pyc
kotti_group_manager/resources.py
kotti_group_manager/resources.pyc
kotti_group_manager/security.py
kotti_group_manager/security.pyc
kotti_group_manager/subscribers.py
kotti_group_manager/subscribers.pyc
kotti_group_manager/alembic/script.py.mako
kotti_group_manager/locale/.gitkeep
kotti_group_manager/static/scripts.js
kotti_group_manager/static/scripts.min.js
kotti_group_manager/static/styles.css
kotti_group_manager/static/styles.min.css
kotti_group_manager/templates/custom-content-alternative.pt
kotti_group_manager/templates/custom-content-default.pt
kotti_group_manager/templates/group.page.pt
kotti_group_manager/templates/group.pt
kotti_group_manager/tests/conftest.py
kotti_group_manager/tests/test_functional.py
kotti_group_manager/tests/test_resources.py
kotti_group_manager/tests/test_view.py
kotti_group_manager/views/__init__.py
kotti_group_manager/views/__init__.pyc
kotti_group_manager/views/edit.py
kotti_group_manager/views/edit.pyc
kotti_group_manager/views/view.py
kotti_group_manager/views/view.pyc
kotti_group_manager-0.1.1.dev0.dist-info/METADATA
kotti_group_manager-0.1.1.dev0.dist-info/RECORD
kotti_group_manager-0.1.1.dev0.dist-info/WHEEL
kotti_group_manager-0.1.1.dev0.dist-info/entry_points.txt
kotti_group_manager-0.1.1.dev0.dist-info/top_level.txt
