Metadata-Version: 2.1
Name: kotti-group-manager
Version: 0.1.1.dev0
Summary: An add-on for Kotti that helps to manage groups
Home-page: https://github.com/Collective-Kotti/kotti_group_manager
Author: Kotti developers
Author-email: kotti@googlegroups.com
License: BSD-derived (http://www.repoze.org/LICENSE.txt)
Keywords: kotti web cms wcms pylons pyramid sqlalchemy bootstrap group
Platform: UNKNOWN
Classifier: Programming Language :: Python
Classifier: Programming Language :: Python :: 2.6
Classifier: Programming Language :: Python :: 2.7
Classifier: Framework :: Pylons
Classifier: Topic :: Internet :: WWW/HTTP
Classifier: Topic :: Internet :: WWW/HTTP :: Dynamic Content
Classifier: Topic :: Internet :: WWW/HTTP :: WSGI :: Application
Classifier: License :: Repoze Public License
Requires-Dist: Kotti (>=1.0.0)
Requires-Dist: kotti-tinymce
Requires-Dist: kotti-controlpanel
Requires-Dist: kotti-toolkit
